sanic_restful/__init__.py
sanic_restful/__version__.py
sanic_restful/api.py
sanic_restful/datastructures.py
sanic_restful/exceptions.py
sanic_restful/fields.py
sanic_restful/json.py
sanic_restful/marshal.py
sanic_restful/reqparse.py
sanic_restful/resource.py
sanic_restful/util.py
sanic_restful-0.0.9.dist-info/AUTHORS.md
sanic_restful-0.0.9.dist-info/LICENSE
sanic_restful-0.0.9.dist-info/METADATA
sanic_restful-0.0.9.dist-info/WHEEL
sanic_restful-0.0.9.dist-info/top_level.txt
sanic_restful-0.0.9.dist-info/RECORD
