Metadata-Version: 2.1
Name: sanic-restful
Version: 0.0.9
Summary: Simple framework for creating REST APIs,Likely Flask-Restful
Home-page: https://github.com/CoCongV/sanic-restful
Author: CoCong
Author-email: cong.lv.yx@gmail.com
License: BSD
Platform: any
Classifier: Environment :: Web Environment
Classifier: Programming Language :: Python :: 3.6
Classifier: License :: OSI Approved :: BSD License
Requires-Dist: aniso8601 (>=0.82)
Requires-Dist: Sanic
Requires-Dist: pytz
Requires-Dist: werkzeug
